scitime/__init__.py
scitime/_config.json
scitime/_log.py
scitime/_model.py
scitime/_utils.py
scitime/estimate.py
scitime/models/NN_KMeans_confint.json
scitime/models/NN_KMeans_estimator.json
scitime/models/NN_KMeans_estimator.pkl
scitime/models/NN_RandomForestClassifier_confint.json
scitime/models/NN_RandomForestClassifier_estimator.json
scitime/models/NN_RandomForestClassifier_estimator.pkl
scitime/models/NN_RandomForestRegressor_confint.json
scitime/models/NN_RandomForestRegressor_estimator.json
scitime/models/NN_RandomForestRegressor_estimator.pkl
scitime/models/NN_SVC_confint.json
scitime/models/NN_SVC_estimator.json
scitime/models/NN_SVC_estimator.pkl
scitime/models/RF_KMeans_estimator.json
scitime/models/RF_KMeans_estimator.pkl
scitime/models/RF_RandomForestClassifier_estimator.json
scitime/models/RF_RandomForestClassifier_estimator.pkl
scitime/models/RF_RandomForestRegressor_estimator.json
scitime/models/RF_RandomForestRegressor_estimator.pkl
scitime/models/RF_SVC_estimator.json
scitime/models/RF_SVC_estimator.pkl
scitime/models/scaler_KMeans_estimator.pkl
scitime/models/scaler_RandomForestClassifier_estimator.pkl
scitime/models/scaler_RandomForestRegressor_estimator.pkl
scitime/models/scaler_SVC_estimator.pkl
scitime-0.0.2.dist-info/LICENSE
scitime-0.0.2.dist-info/METADATA
scitime-0.0.2.dist-info/WHEEL
scitime-0.0.2.dist-info/top_level.txt
scitime-0.0.2.dist-info/RECORD
