Metadata-Version: 2.1
Name: scitime
Version: 0.0.2
Summary: Training time estimator for scikit-learn algorithms
Home-page: http://github.com/nathan-toubiana/scitime
Author: Gabriel Lerner & Nathan Toubiana
Author-email: toubiana.nathan@gmail.com
License: UNKNOWN
Keywords: machine-learning,scikit-learn,training-time
Platform: UNKNOWN
Requires-Python: >=3
Requires-Dist: joblib (>=0.12.5)
Requires-Dist: pandas (>=0.20.3)
Requires-Dist: psutil (>=5.4.7)
Requires-Dist: scikit-learn (>=0.19.1)
